LICENSE.txt
MANIFEST.in
README.rst
setup.py
tw2/__init__.py
tw2.polymaps.egg-info/PKG-INFO
tw2.polymaps.egg-info/SOURCES.txt
tw2.polymaps.egg-info/dependency_links.txt
tw2.polymaps.egg-info/entry_points.txt
tw2.polymaps.egg-info/namespace_packages.txt
tw2.polymaps.egg-info/not-zip-safe
tw2.polymaps.egg-info/requires.txt
tw2.polymaps.egg-info/top_level.txt
tw2/polymaps/__init__.py
tw2/polymaps/defaults.py
tw2/polymaps/geojsonify.py
tw2/polymaps/resources.py
tw2/polymaps/samples.py
tw2/polymaps/widgets.py
tw2/polymaps/static/custom/css/tw2.polymaps-example1.css
tw2/polymaps/static/custom/css/tw2.polymaps-example2.css
tw2/polymaps/static/custom/js/tw2.polymaps.js
tw2/polymaps/static/polymaps/2.4.0/.DS_Store
tw2/polymaps/static/polymaps/2.4.0/polymaps.min.js
tw2/polymaps/templates/__init__.py
tw2/polymaps/templates/polymap.mak